Metadata-Version: 2.1
Name: orthojax
Version: 0.1.5
Summary: Orthogonal polynomials in Jxax
Home-page: https://github.com/PredictiveScienceLab/orthojax
Author: Iilias Bilionis
Author-email: ibilion@purdue.edu
License: MIT License
Classifier: Development Status :: 1 - Planning
Classifier: Intended Audience :: Science/Research
Classifier: License :: OSI Approved :: MIT License
Classifier: Operating System :: OS Independent
Classifier: Programming Language :: Python :: 3
License-File: LICENSE
